LICENSE
MANIFEST.in
README.md
requirements.txt
setup.cfg
setup.py
chainerui/__init__.py
chainerui/_version.py
chainerui/app.py
chainerui/database.py
chainerui/logging.py
chainerui/server.py
chainerui/summary.py
chainerui.egg-info/PKG-INFO
chainerui.egg-info/SOURCES.txt
chainerui.egg-info/dependency_links.txt
chainerui.egg-info/entry_points.txt
chainerui.egg-info/requires.txt
chainerui.egg-info/top_level.txt
chainerui/client/__init__.py
chainerui/client/client.py
chainerui/client/helper.py
chainerui/extensions/__init__.py
chainerui/extensions/commands_extension.py
chainerui/migration/__init__.py
chainerui/migration/env.py
chainerui/migration/versions/00a907e5780f_add_log_modified_at.py
chainerui/migration/versions/1104edb51c0d_add_project_table.py
chainerui/migration/versions/213e2a3392f2_init.py
chainerui/migration/versions/4e779a5fc57e_add_is_unregistered_to_result.py
chainerui/migration/versions/6cc68bf684ac_add_project_id_to_result.py
chainerui/migration/versions/6cd7f193a3de_create_data.py
chainerui/migration/versions/7fcaf5b6e9e8_add_request_and_response_to_command.py
chainerui/migration/versions/9d002f65344b_add_crawlable.py
chainerui/migration/versions/__init__.py
chainerui/migration/versions/c29d1b4b67fe_add_result_log_index.py
chainerui/migration/versions/c78d4004717f_add_timestamps_to_result.py
chainerui/migration/versions/e3db52a480f8_alter_log_data_type.py
chainerui/models/__init__.py
chainerui/models/argument.py
chainerui/models/asset.py
chainerui/models/bindata.py
chainerui/models/command.py
chainerui/models/log.py
chainerui/models/project.py
chainerui/models/result.py
chainerui/models/snapshot.py
chainerui/report/__init__.py
chainerui/report/audio_report.py
chainerui/report/image_report.py
chainerui/report/utils.py
chainerui/static/dist/chainerui.css
chainerui/static/dist/chainerui.js
chainerui/static/dist/fa-brands-400.eot
chainerui/static/dist/fa-brands-400.svg
chainerui/static/dist/fa-brands-400.ttf
chainerui/static/dist/fa-brands-400.woff
chainerui/static/dist/fa-brands-400.woff2
chainerui/static/dist/fa-regular-400.eot
chainerui/static/dist/fa-regular-400.svg
chainerui/static/dist/fa-regular-400.ttf
chainerui/static/dist/fa-regular-400.woff
