Metadata-Version: 2.1
Name: chainerui
Version: 0.10.0.1
Summary: ChainerUI: User Interface for Chainer
Home-page: https://github.com/chainer/chainerui
Author: 
Author-email: 
License: UNKNOWN
Platform: UNKNOWN
Provides-Extra: test-ci
Provides-Extra: stylecheck
Provides-Extra: test
Provides-Extra: docs
Provides-Extra: test-ci-plain
